README.md
setup.py
jupytest/__init__.py
jupytest.egg-info/PKG-INFO
jupytest.egg-info/SOURCES.txt
jupytest.egg-info/dependency_links.txt
jupytest.egg-info/requires.txt
jupytest.egg-info/top_level.txt