Metadata-Version: 1.2
Name: jupytest
Version: 1.0.3
Summary: Unit and integration testing in a Jupyter notebook
Home-page: https://github.com/hamelin/jupytest
Author: Benoit Hamelin
Author-email: benoit@benoithamelin.com
License: BSD 3-Clause
Platform: UNKNOWN
Requires-Python: >=3.6
